{
    "version": "0.4",
    "title": "Career details",
    "type": "page",
    "metadata": {
        "template_type": "single-page",
        "include_in_zip": "1",
        "elementor_pro_required": null,
        "wp_page_template": "default"
    },
    "content": [
        {
            "id": "440ddb91",
            "settings": {
                "background_background": "classic",
                "background_image": {
                    "id": 1080,
                    "url": "https:\/\/demo.bosathemes.com\/unbound\/wp-content\/uploads\/sites\/10\/2021\/08\/unbound-img49.jpg",
                    "alt": "",
                    "source": "library"
                },
                "background_position": "top center",
                "background_repeat": "no-repeat",
                "background_size": "cover",
                "background_overlay_background": "classic",
                "background_overlay_opacity": {
                    "unit": "px",
                    "size": 0.7,
                    "sizes": []
                },
                "_title": "inner-banner",
                "margin": {
                    "unit": "px",
                    "top": "-195",
                    "right": 0,
                    "bottom": "100",
                    "left": 0,
                    "isLinked": false
                },
                "shape_divider_bottom_width": {
                    "unit": "%",
                    "size": 100,
                    "sizes": []
                },
                "shape_divider_bottom_negative": "yes",
                "shape_divider_top_height": {
                    "unit": "px",
                    "size": 15,
                    "sizes": []
                },
                "padding": {
                    "unit": "px",
                    "top": "0",
                    "right": "15",
                    "bottom": "0",
                    "left": "15",
                    "isLinked": false
                },
                "__globals__": {
                    "background_overlay_color": "globals\/colors?id=e5e9561"
                },
                "gap": "no",
                "margin_tablet": {
                    "unit": "px",
                    "top": "-165",
                    "right": 0,
                    "bottom": "100",
                    "left": 0,
                    "isLinked": false
                },
                "margin_mobile": {
                    "unit": "px",
                    "top": "-265",
                    "right": 0,
                    "bottom": "80",
                    "left": 0,
                    "isLinked": false
                },
                "height": "min-height",
                "custom_height": {
                    "unit": "px",
                    "size": 550,
                    "sizes": []
                },
                "custom_height_tablet": {
                    "unit": "px",
                    "size": 500,
                    "sizes": []
                },
                "custom_height_mobile": {
                    "unit": "px",
                    "size": 550,
                    "sizes": []
                },
                "pa_condition_repeater": []
            },
            "elements": [
                {
                    "id": "4f4882fd",
                    "settings": {
                        "_column_size": 100,
                        "_inline_size": null,
                        "background_background": "classic",
                        "background_position": "initial",
                        "background_position_tablet": "initial",
                        "background_position_mobile": "initial",
                        "background_xpos": {
                            "unit": "%",
                            "size": 100,
                            "sizes": []
                        },
                        "background_xpos_tablet": {
                            "unit": "%",
                            "size": 100,
                            "sizes": []
                        },
                        "background_xpos_mobile": {
                            "unit": "%",
                            "size": 100,
                            "sizes": []
                        },
                        "background_ypos": {
                            "unit": "%",
                            "size": 50,
                            "sizes": []
                        },
                        "background_ypos_tablet": {
                            "unit": "px",
                            "size": 85,
                            "sizes": []
                        },
                        "background_ypos_mobile": {
                            "unit": "%",
                            "size": 85,
                            "sizes": []
                        },
                        "background_repeat": "no-repeat",
                        "background_size": "initial",
                        "background_size_mobile": "initial",
                        "background_bg_width": {
                            "unit": "%",
                            "size": 36,
                            "sizes": []
                        },
                        "background_bg_width_mobile": {
                            "unit": "%",
                            "size": 40,
                            "sizes": []
                        },
                        "padding": {
                            "unit": "px",
                            "top": "150",
                            "right": "0",
                            "bottom": "0",
                            "left": "0",
                            "isLinked": false
                        },
                        "margin_tablet": {
                            "unit": "%",
                            "top": "",
                            "right": "",
                            "bottom": "",
                            "left": "",
                            "isLinked": true
                        },
                        "padding_tablet": {
                            "unit": "px",
                            "top": "120",
                            "right": "0",
                            "bottom": "0",
                            "left": "0",
                            "isLinked": false
                        },
                        "padding_mobile": {
                            "unit": "px",
                            "top": "200",
                            "right": "0",
                            "bottom": "0",
                            "left": "0",
                            "isLinked": false
                        },
                        "pa_condition_repeater": []
                    },
                    "elements": [
                        {
                            "id": "3883071",
                            "settings": {
                                "title": "Career details",
                                "header_size": "h1",
                                "align": "center",
                                "typography_font_family": "Montserrat",
                                "typography_font_size": {
                                    "unit": "px",
                                    "size": 55,
                                    "sizes": []
                                },
                                "typography_font_size_tablet": {
                                    "unit": "px",
                                    "size": 45,
                                    "sizes": []
                                },
                                "typography_font_size_mobile": {
                                    "unit": "px",
                                    "size": 35,
                                    "sizes": []
                                },
                                "typography_font_weight": "800",
                                "typography_text_transform": "uppercase",
                                "typography_line_height": {
                                    "unit": "em",
                                    "size": 1.1,
                                    "sizes": []
                                },
                                "__globals__": {
                                    "title_color": "globals\/colors?id=21bfb04"
                                },
                                "pa_condition_repeater": []
                            },
                            "elements": [],
                            "isInner": false,
                            "widgetType": "heading",
                            "elType": "widget"
                        }
                    ],
                    "isInner": false,
                    "elType": "column"
                }
            ],
            "isInner": false,
            "elType": "section"
        },
        {
            "id": "288ffbd5",
            "settings": {
                "gap": "no",
                "structure": "20",
                "padding": {
                    "unit": "px",
                    "top": "0",
                    "right": "15",
                    "bottom": "0",
                    "left": "15",
                    "isLinked": false
                },
                "_title": "career-detail",
                "background_overlay_position": "bottom right",
                "background_overlay_repeat": "no-repeat",
                "background_overlay_opacity": {
                    "unit": "px",
                    "size": 0.15,
                    "sizes": []
                },
                "padding_tablet": {
                    "unit": "px",
                    "top": "0",
                    "right": "15",
                    "bottom": "0",
                    "left": "15",
                    "isLinked": false
                },
                "reverse_order_tablet": "reverse-tablet",
                "reverse_order_mobile": "reverse-mobile",
                "margin": {
                    "unit": "px",
                    "top": "0",
                    "right": 0,
                    "bottom": "100",
                    "left": 0,
                    "isLinked": false
                },
                "margin_tablet": {
                    "unit": "px",
                    "top": "0",
                    "right": 0,
                    "bottom": "100",
                    "left": 0,
                    "isLinked": false
                },
                "margin_mobile": {
                    "unit": "px",
                    "top": "0",
                    "right": 0,
                    "bottom": "80",
                    "left": 0,
                    "isLinked": false
                },
                "pa_condition_repeater": []
            },
            "elements": [
                {
                    "id": "5e0a4479",
                    "settings": {
                        "_column_size": 50,
                        "_inline_size": 34,
                        "_inline_size_tablet": 100,
                        "pa_condition_repeater": []
                    },
                    "elements": [
                        {
                            "id": "5787a4a6",
                            "settings": {
                                "pa_condition_repeater": []
                            },
                            "elements": [
                                {
                                    "id": "8c6fda2",
                                    "settings": {
                                        "_column_size": 100,
                                        "_inline_size": null,
                                        "background_background": "classic",
                                        "margin": {
                                            "unit": "px",
                                            "top": "0",
                                            "right": "0",
                                            "bottom": "50",
                                            "left": "0",
                                            "isLinked": false
                                        },
                                        "padding": {
                                            "unit": "px",
                                            "top": "30",
                                            "right": "30",
                                            "bottom": "26",
                                            "left": "30",
                                            "isLinked": false
                                        },
                                        "border_border": "solid",
                                        "border_width": {
                                            "unit": "px",
                                            "top": "0",
                                            "right": "0",
                                            "bottom": "3",
                                            "left": "0",
                                            "isLinked": false
                                        },
                                        "padding_mobile": {
                                            "unit": "px",
                                            "top": "20",
                                            "right": "20",
                                            "bottom": "17",
                                            "left": "20",
                                            "isLinked": false
                                        },
                                        "__globals__": {
                                            "border_color": "globals\/colors?id=primary",
                                            "background_color": "globals\/colors?id=ad41708"
                                        },
                                        "border_radius": {
                                            "unit": "px",
                                            "top": "25",
                                            "right": "25",
                                            "bottom": "25",
                                            "left": "25",
                                            "isLinked": true
                                        },
                                        "pa_condition_repeater": []
                                    },
                                    "elements": [
                                        {
                                            "id": "2bf5084d",
                                            "settings": {
                                                "title": "How to apply?",
                                                "header_size": "h5",
                                                "align": "center",
                                                "_margin": {
                                                    "unit": "px",
                                                    "top": "0",
                                                    "right": "0",
                                                    "bottom": "4",
                                                    "left": "0",
                                                    "isLinked": false
                                                },
                                                "_padding": {
                                                    "unit": "px",
                                                    "top": "10",
                                                    "right": "10",
                                                    "bottom": "10",
                                                    "left": "10",
                                                    "isLinked": true
                                                },
                                                "_background_background": "classic",
                                                "__globals__": {
                                                    "_background_color": "globals\/colors?id=secondary",
                                                    "title_color": "globals\/colors?id=21bfb04",
                                                    "typography_typography": "globals\/typography?id=99dd0b2"
                                                },
                                                "title_color": "#FFFFFF",
                                                "_background_color": "#F15B43",
                                                "_border_radius": {
                                                    "unit": "px",
                                                    "top": "25",
                                                    "right": "25",
                                                    "bottom": "25",
                                                    "left": "25",
                                                    "isLinked": true
                                                },
                                                "pa_condition_repeater": []
                                            },
                                            "elements": [],
                                            "isInner": false,
                                            "widgetType": "heading",
                                            "elType": "widget"
                                        },
                                        {
                                            "id": "1739bb52",
                                            "settings": {
                                                "icon_list": [
                                                    {
                                                        "text": "Nunc expedita montes minima.",
                                                        "selected_icon": {
                                                            "value": "fas fa-minus",
                                                            "library": "fa-solid"
                                                        },
                                                        "_id": "6de9337"
                                                    },
                                                    {
                                                        "text": "Animi atque ornare iaculis.",
                                                        "selected_icon": {
                                                            "value": "fas fa-minus",
                                                            "library": "fa-solid"
                                                        },
                                                        "_id": "9060b2e"
                                                    },
                                                    {
                                                        "text": "Sociosqu scelerisque adipisci.",
                                                        "selected_icon": {
                                                            "value": "fas fa-minus",
                                                            "library": "fa-solid"
                                                        },
                                                        "_id": "c3834ad"
                                                    },
                                                    {
                                                        "text": "Purus eveniet incidi dunt.",
                                                        "selected_icon": {
                                                            "value": "fas fa-minus",
                                                            "library": "fa-solid"
                                                        },
                                                        "_id": "3deb823"
                                                    },
                                                    {
                                                        "text": "Animi atque ornare iaculis.",
                                                        "selected_icon": {
                                                            "value": "fas fa-minus",
                                                            "library": "fa-solid"
                                                        },
                                                        "_id": "1a6b5fe"
                                                    }
                                                ],
                                                "space_between": {
                                                    "unit": "px",
                                                    "size": 5,
                                                    "sizes": []
                                                },
                                                "icon_typography_font_size": {
                                                    "unit": "px",
                                                    "size": 15,
                                                    "sizes": []
                                                },
                                                "icon_typography_font_weight": "500",
                                                "_margin": {
                                                    "unit": "px",
                                                    "top": "0",
                                                    "right": "0",
                                                    "bottom": "0",
                                                    "left": "0",
                                                    "isLinked": false
                                                },
                                                "icon_typography_font_size_mobile": {
                                                    "unit": "px",
                                                    "size": 15,
                                                    "sizes": []
                                                },
                                                "__globals__": {
                                                    "icon_color": "globals\/colors?id=primary"
                                                },
                                                "pa_condition_repeater": []
                                            },
                                            "elements": [],
                                            "isInner": false,
                                            "widgetType": "icon-list",
                                            "elType": "widget"
                                        }
                                    ],
                                    "isInner": true,
                                    "elType": "column"
                                }
                            ],
                            "isInner": true,
                            "elType": "section"
                        },
                        {
                            "id": "478ebfa8",
                            "settings": {
                                "gap": "no",
                                "pa_condition_repeater": []
                            },
                            "elements": [
                                {
                                    "id": "ef62885",
                                    "settings": {
                                        "_column_size": 100,
                                        "_inline_size": null,
                                        "background_background": "classic",
                                        "padding": {
                                            "unit": "px",
                                            "top": "30",
                                            "right": "30",
                                            "bottom": "10",
                                            "left": "30",
                                            "isLinked": false
                                        },
                                        "border_border": "solid",
                                        "border_width": {
                                            "unit": "px",
                                            "top": "0",
                                            "right": "0",
                                            "bottom": "3",
                                            "left": "0",
                                            "isLinked": false
                                        },
                                        "margin": {
                                            "unit": "px",
                                            "top": "0",
                                            "right": "0",
                                            "bottom": "50",
                                            "left": "0",
                                            "isLinked": false
                                        },
                                        "padding_mobile": {
                                            "unit": "px",
                                            "top": "20",
                                            "right": "20",
                                            "bottom": "0",
                                            "left": "20",
                                            "isLinked": false
                                        },
                                        "__globals__": {
                                            "border_color": "globals\/colors?id=secondary",
                                            "background_color": "globals\/colors?id=ad41708"
                                        },
                                        "border_radius": {
                                            "unit": "px",
                                            "top": "25",
                                            "right": "25",
                                            "bottom": "25",
                                            "left": "25",
                                            "isLinked": true
                                        },
                                        "pa_condition_repeater": []
                                    },
                                    "elements": [
                                        {
                                            "id": "565fc99c",
                                            "settings": {
                                                "title": "Frequently Asked Questions",
                                                "header_size": "h5",
                                                "align": "center",
                                                "_margin": {
                                                    "unit": "px",
                                                    "top": "0",
                                                    "right": "0",
                                                    "bottom": "4",
                                                    "left": "0",
                                                    "isLinked": false
                                                },
                                                "_padding": {
                                                    "unit": "px",
                                                    "top": "10",
                                                    "right": "10",
                                                    "bottom": "10",
                                                    "left": "10",
                                                    "isLinked": true
                                                },
                                                "_background_background": "classic",
                                                "__globals__": {
                                                    "_background_color": "globals\/colors?id=secondary",
                                                    "title_color": "globals\/colors?id=21bfb04",
                                                    "typography_typography": "globals\/typography?id=99dd0b2"
                                                },
                                                "title_color": "#FFFFFF",
                                                "_background_color": "#F15B43",
                                                "_border_radius": {
                                                    "unit": "px",
                                                    "top": "25",
                                                    "right": "25",
                                                    "bottom": "25",
                                                    "left": "25",
                                                    "isLinked": true
                                                },
                                                "pa_condition_repeater": []
                                            },
                                            "elements": [],
                                            "isInner": false,
                                            "widgetType": "heading",
                                            "elType": "widget"
                                        },
                                        {
                                            "id": "7f4aa67b",
                                            "settings": {
                                                "tabs": [
                                                    {
                                                        "tab_title": "When the announcements?",
                                                        "tab_content": "Lorem ipsum dolor sit amet, consectetur adipiscing elit. Ut elit tellus, luctus nec ullamcorper mattis, pulvinar dapibus leo.",
                                                        "_id": "0348e40"
                                                    },
                                                    {
                                                        "tab_title": "Can i apply after rejection?",
                                                        "tab_content": "Lorem ipsum dolor sit amet, consectetur adipiscing elit. Ut elit tellus, luctus nec ullamcorper mattis, pulvinar dapibus leo.",
                                                        "_id": "ba26de5"
                                                    },
                                                    {
                                                        "tab_title": "Where to interview?",
                                                        "tab_content": "Lorem ipsum dolor sit amet, consectetur adipiscing elit. Ut elit tellus, luctus nec ullamcorper mattis, pulvinar dapibus leo.",
                                                        "_id": "7f7fc20"
                                                    }
                                                ],
                                                "selected_icon": {
                                                    "value": "fas fa-angle-down",
                                                    "library": "fa-solid"
                                                },
                                                "selected_active_icon": {
                                                    "value": "fas fa-angle-up",
                                                    "library": "fa-solid"
                                                },
                                                "border_width": {
                                                    "unit": "px",
                                                    "size": 0,
                                                    "sizes": []
                                                },
                                                "space_between": {
                                                    "unit": "px",
                                                    "size": 20,
                                                    "sizes": []
                                                },
                                                "title_background": "#FFFFFF",
                                                "title_padding": {
                                                    "unit": "px",
                                                    "top": "18",
                                                    "right": "18",
                                                    "bottom": "18",
                                                    "left": "18",
                                                    "isLinked": true
                                                },
                                                "icon_align": "right",
                                                "content_typography_font_size": {
                                                    "unit": "px",
                                                    "size": 16,
                                                    "sizes": []
                                                },
                                                "content_typography_font_weight": "normal",
                                                "content_padding": {
                                                    "unit": "px",
                                                    "top": "0",
                                                    "right": "20",
                                                    "bottom": "20",
                                                    "left": "20",
                                                    "isLinked": false
                                                },
                                                "faq_schema": "yes",
                                                "box_shadow_box_shadow_type": "yes",
                                                "box_shadow_box_shadow": {
                                                    "horizontal": 0,
                                                    "vertical": 0,
                                                    "blur": 13,
                                                    "spread": -4,
                                                    "color": "rgba(0, 0, 0, 0.2)"
                                                },
                                                "content_background_color": "#FFFFFF",
                                                "__globals__": {
                                                    "tab_active_color": "",
                                                    "title_typography_typography": "globals\/typography?id=accent",
                                                    "content_background_color": "globals\/colors?id=21bfb04",
                                                    "content_typography_typography": "",
                                                    "title_color": "globals\/colors?id=text"
                                                },
                                                "title_html_tag": "h5",
                                                "title_color": "#333333",
                                                "content_typography_font_family": "Prompt",
                                                "content_typography_line_height": {
                                                    "unit": "em",
                                                    "size": 1.5,
                                                    "sizes": []
                                                },
                                                "pa_condition_repeater": []
                                            },
                                            "elements": [],
                                            "isInner": false,
                                            "widgetType": "toggle",
                                            "elType": "widget"
                                        }
                                    ],
                                    "isInner": true,
                                    "elType": "column"
                                }
                            ],
                            "isInner": true,
                            "elType": "section"
                        },
                        {
                            "id": "56bc766f",
                            "settings": {
                                "gap": "no",
                                "pa_condition_repeater": []
                            },
                            "elements": [
                                {
                                    "id": "4084268",
                                    "settings": {
                                        "_column_size": 100,
                                        "_inline_size": null,
                                        "background_background": "classic",
                                        "padding": {
                                            "unit": "px",
                                            "top": "30",
                                            "right": "30",
                                            "bottom": "30",
                                            "left": "30",
                                            "isLinked": true
                                        },
                                        "space_between_widgets": 18,
                                        "background_overlay_background": "classic",
                                        "background_overlay_position": "bottom right",
                                        "background_overlay_repeat": "no-repeat",
                                        "background_overlay_size": "contain",
                                        "background_overlay_opacity": {
                                            "unit": "px",
                                            "size": 0.3,
                                            "sizes": []
                                        },
                                        "border_border": "solid",
                                        "border_width": {
                                            "unit": "px",
                                            "top": "0",
                                            "right": "0",
                                            "bottom": "3",
                                            "left": "0",
                                            "isLinked": false
                                        },
                                        "__globals__": {
                                            "border_color": "globals\/colors?id=primary",
                                            "background_color": "globals\/colors?id=ad41708"
                                        },
                                        "border_radius": {
                                            "unit": "px",
                                            "top": "25",
                                            "right": "25",
                                            "bottom": "25",
                                            "left": "25",
                                            "isLinked": true
                                        },
                                        "pa_condition_repeater": []
                                    },
                                    "elements": [
                                        {
                                            "id": "b1f798d",
                                            "settings": {
                                                "selected_icon": {
                                                    "value": "fas fa-file-invoice",
                                                    "library": "fa-solid"
                                                },
                                                "view": "stacked",
                                                "secondary_color": "#FFFFFF",
                                                "__globals__": {
                                                    "primary_color": "globals\/colors?id=primary"
                                                },
                                                "pa_condition_repeater": []
                                            },
                                            "elements": [],
                                            "isInner": false,
                                            "widgetType": "icon",
                                            "elType": "widget"
                                        },
                                        {
                                            "id": "5fee5e51",
                                            "settings": {
                                                "title": "Send us your C.V.",
                                                "header_size": "h5",
                                                "align": "center",
                                                "typography_font_size": {
                                                    "unit": "px",
                                                    "size": 22,
                                                    "sizes": []
                                                },
                                                "typography_font_size_mobile": {
                                                    "unit": "px",
                                                    "size": 25,
                                                    "sizes": []
                                                },
                                                "align_mobile": "center",
                                                "pa_condition_repeater": []
                                            },
                                            "elements": [],
                                            "isInner": false,
                                            "widgetType": "heading",
                                            "elType": "widget"
                                        },
                                        {
                                            "id": "73be1a01",
                                            "settings": {
                                                "editor": "<p>Do you want to work with us? Please, send your CV to <a href=\"#\">domain123@gmail.com<\/a><\/p>",
                                                "typography_font_family": "Poppins",
                                                "typography_font_size": {
                                                    "unit": "px",
                                                    "size": 16,
                                                    "sizes": []
                                                },
                                                "typography_font_weight": "normal",
                                                "typography_line_height": {
                                                    "unit": "em",
                                                    "size": 1.5,
                                                    "sizes": []
                                                },
                                                "align": "center",
                                                "_padding_tablet": {
                                                    "unit": "px",
                                                    "top": "0",
                                                    "right": "0",
                                                    "bottom": "0",
                                                    "left": "0",
                                                    "isLinked": false
                                                },
                                                "_padding_mobile": {
                                                    "unit": "px",
                                                    "top": "0",
                                                    "right": "0",
                                                    "bottom": "0",
                                                    "left": "0",
                                                    "isLinked": false
                                                },
                                                "align_mobile": "center",
                                                "_margin": {
                                                    "unit": "px",
                                                    "top": "0",
                                                    "right": "0",
                                                    "bottom": "-14",
                                                    "left": "0",
                                                    "isLinked": false
                                                },
                                                "pa_condition_repeater": []
                                            },
                                            "elements": [],
                                            "isInner": false,
                                            "widgetType": "text-editor",
                                            "elType": "widget"
                                        },
                                        {
                                            "id": "1a70f62e",
                                            "settings": {
                                                "width": {
                                                    "unit": "%",
                                                    "size": 50,
                                                    "sizes": []
                                                },
                                                "align": "center",
                                                "look": "line_text",
                                                "text": "Or",
                                                "gap": {
                                                    "unit": "px",
                                                    "size": 5,
                                                    "sizes": []
                                                },
                                                "__globals__": {
                                                    "text_color": "globals\/colors?id=primary",
                                                    "typography_typography": "globals\/typography?id=2bd9da1",
                                                    "color": ""
                                                },
                                                "color": "#F15B4359",
                                                "text_color": "#F15B43",
                                                "pa_condition_repeater": []
                                            },
                                            "elements": [],
                                            "isInner": false,
                                            "widgetType": "divider",
                                            "elType": "widget"
                                        },
                                        {
                                            "id": "3f783985",
                                            "settings": {
                                                "text": "CONTACT US",
                                                "align": "center",
                                                "typography_font_family": "Montserrat",
                                                "typography_font_size": {
                                                    "unit": "px",
                                                    "size": 15,
                                                    "sizes": []
                                                },
                                                "typography_font_weight": "600",
                                                "typography_text_transform": "uppercase",
                                                "typography_line_height": {
                                                    "unit": "em",
                                                    "size": 1,
                                                    "sizes": []
                                                },
                                                "button_hover_border_color": "#030F27",
                                                "border_width": {
                                                    "unit": "px",
                                                    "top": "1",
                                                    "right": "1",
                                                    "bottom": "1",
                                                    "left": "1",
                                                    "isLinked": true
                                                },
                                                "typography_font_size_mobile": {
                                                    "unit": "px",
                                                    "size": 15,
                                                    "sizes": []
                                                },
                                                "text_padding_mobile": {
                                                    "unit": "px",
                                                    "top": "18",
                                                    "right": "25",
                                                    "bottom": "18",
                                                    "left": "25",
                                                    "isLinked": false
                                                },
                                                "align_mobile": "center",
                                                "align_tablet": "center",
                                                "_margin": {
                                                    "unit": "px",
                                                    "top": "2",
                                                    "right": "0",
                                                    "bottom": "0",
                                                    "left": "0",
                                                    "isLinked": false
                                                },
                                                "pa_condition_repeater": []
                                            },
                                            "elements": [],
                                            "isInner": false,
                                            "widgetType": "button",
                                            "elType": "widget"
                                        }
                                    ],
                                    "isInner": true,
                                    "elType": "column"
                                }
                            ],
                            "isInner": true,
                            "elType": "section"
                        }
                    ],
                    "isInner": false,
                    "elType": "column"
                },
                {
                    "id": "5de10666",
                    "settings": {
                        "_column_size": 50,
                        "_inline_size": 66,
                        "padding": {
                            "unit": "px",
                            "top": "0",
                            "right": "0",
                            "bottom": "0",
                            "left": "40",
                            "isLinked": false
                        },
                        "_inline_size_tablet": 100,
                        "padding_tablet": {
                            "unit": "px",
                            "top": "0",
                            "right": "0",
                            "bottom": "50",
                            "left": "0",
                            "isLinked": false
                        },
                        "pa_condition_repeater": []
                    },
                    "elements": [
                        {
                            "id": "31b76cbc",
                            "settings": {
                                "gap": "no",
                                "structure": "30",
                                "background_background": "classic",
                                "margin": {
                                    "unit": "px",
                                    "top": "",
                                    "right": 0,
                                    "bottom": "",
                                    "left": 0,
                                    "isLinked": true
                                },
                                "padding": {
                                    "unit": "px",
                                    "top": "22",
                                    "right": "22",
                                    "bottom": "20",
                                    "left": "22",
                                    "isLinked": false
                                },
                                "padding_mobile": {
                                    "unit": "px",
                                    "top": "8",
                                    "right": "10",
                                    "bottom": "8",
                                    "left": "10",
                                    "isLinked": false
                                },
                                "__globals__": {
                                    "background_color": "globals\/colors?id=accent"
                                },
                                "border_radius": {
                                    "unit": "px",
                                    "top": "25",
                                    "right": "25",
                                    "bottom": "0",
                                    "left": "0",
                                    "isLinked": false
                                },
                                "pa_condition_repeater": []
                            },
                            "elements": [
                                {
                                    "id": "343a9776",
                                    "settings": {
                                        "_column_size": 33,
                                        "_inline_size": null,
                                        "space_between_widgets": 0,
                                        "border_border": "solid",
                                        "border_width": {
                                            "unit": "px",
                                            "top": "0",
                                            "right": "2",
                                            "bottom": "0",
                                            "left": "0",
                                            "isLinked": false
                                        },
                                        "border_width_mobile": {
                                            "unit": "px",
                                            "top": "0",
                                            "right": "0",
                                            "bottom": "2",
                                            "left": "0",
                                            "isLinked": false
                                        },
                                        "border_color": "#FFFFFF47",
                                        "padding": {
                                            "unit": "px",
                                            "top": "0",
                                            "right": "10",
                                            "bottom": "0",
                                            "left": "10",
                                            "isLinked": false
                                        },
                                        "padding_mobile": {
                                            "unit": "px",
                                            "top": "15",
                                            "right": "15",
                                            "bottom": "21",
                                            "left": "15",
                                            "isLinked": false
                                        },
                                        "pa_condition_repeater": []
                                    },
                                    "elements": [
                                        {
                                            "id": "49896b87",
                                            "settings": {
                                                "title": "Post :",
                                                "header_size": "h6",
                                                "align": "center",
                                                "align_mobile": "center",
                                                "_margin": {
                                                    "unit": "px",
                                                    "top": "0",
                                                    "right": "0",
                                                    "bottom": "8",
                                                    "left": "0",
                                                    "isLinked": false
                                                },
                                                "__globals__": {
                                                    "title_color": "globals\/colors?id=21bfb04",
                                                    "typography_typography": "globals\/typography?id=secondary"
                                                },
                                                "pa_condition_repeater": []
                                            },
                                            "elements": [],
                                            "isInner": false,
                                            "widgetType": "heading",
                                            "elType": "widget"
                                        },
                                        {
                                            "id": "2d86c3fd",
                                            "settings": {
                                                "title": "Volunteer",
                                                "header_size": "h5",
                                                "align": "center",
                                                "align_mobile": "center",
                                                "__globals__": {
                                                    "title_color": "globals\/colors?id=21bfb04",
                                                    "typography_typography": "globals\/typography?id=99dd0b2"
                                                },
                                                "pa_condition_repeater": []
                                            },
                                            "elements": [],
                                            "isInner": false,
                                            "widgetType": "heading",
                                            "elType": "widget"
                                        }
                                    ],
                                    "isInner": true,
                                    "elType": "column"
                                },
                                {
                                    "id": "331d6116",
                                    "settings": {
                                        "_column_size": 33,
                                        "_inline_size": null,
                                        "space_between_widgets": 0,
                                        "border_border": "solid",
                                        "border_width": {
                                            "unit": "px",
                                            "top": "0",
                                            "right": "2",
                                            "bottom": "0",
                                            "left": "0",
                                            "isLinked": false
                                        },
                                        "border_width_mobile": {
                                            "unit": "px",
                                            "top": "0",
                                            "right": "0",
                                            "bottom": "2",
                                            "left": "0",
                                            "isLinked": false
                                        },
                                        "border_color": "#FFFFFF47",
                                        "padding": {
                                            "unit": "px",
                                            "top": "0",
                                            "right": "10",
                                            "bottom": "0",
                                            "left": "10",
                                            "isLinked": false
                                        },
                                        "padding_mobile": {
                                            "unit": "px",
                                            "top": "21",
                                            "right": "15",
                                            "bottom": "21",
                                            "left": "15",
                                            "isLinked": false
                                        },
                                        "pa_condition_repeater": []
                                    },
                                    "elements": [
                                        {
                                            "id": "59cdc989",
                                            "settings": {
                                                "title": "Time :",
                                                "header_size": "h6",
                                                "align": "center",
                                                "align_mobile": "center",
                                                "_margin": {
                                                    "unit": "px",
                                                    "top": "0",
                                                    "right": "0",
                                                    "bottom": "8",
                                                    "left": "0",
                                                    "isLinked": false
                                                },
                                                "__globals__": {
                                                    "title_color": "globals\/colors?id=21bfb04",
                                                    "typography_typography": "globals\/typography?id=secondary"
                                                },
                                                "pa_condition_repeater": []
                                            },
                                            "elements": [],
                                            "isInner": false,
                                            "widgetType": "heading",
                                            "elType": "widget"
                                        },
                                        {
                                            "id": "72a6a84a",
                                            "settings": {
                                                "title": "Full Time",
                                                "header_size": "h5",
                                                "align": "center",
                                                "align_mobile": "center",
                                                "__globals__": {
                                                    "title_color": "globals\/colors?id=21bfb04",
                                                    "typography_typography": "globals\/typography?id=99dd0b2"
                                                },
                                                "pa_condition_repeater": []
                                            },
                                            "elements": [],
                                            "isInner": false,
                                            "widgetType": "heading",
                                            "elType": "widget"
                                        }
                                    ],
                                    "isInner": true,
                                    "elType": "column"
                                },
                                {
                                    "id": "34c7a075",
                                    "settings": {
                                        "_column_size": 33,
                                        "_inline_size": null,
                                        "space_between_widgets": 0,
                                        "border_border": "solid",
                                        "border_width": {
                                            "unit": "px",
                                            "top": "0",
                                            "right": "0",
                                            "bottom": "0",
                                            "left": "0",
                                            "isLinked": false
                                        },
                                        "border_color": "#FFFFFFA8",
                                        "padding": {
                                            "unit": "px",
                                            "top": "0",
                                            "right": "10",
                                            "bottom": "0",
                                            "left": "10",
                                            "isLinked": false
                                        },
                                        "padding_mobile": {
                                            "unit": "px",
                                            "top": "21",
                                            "right": "15",
                                            "bottom": "15",
                                            "left": "15",
                                            "isLinked": false
                                        },
                                        "pa_condition_repeater": []
                                    },
                                    "elements": [
                                        {
                                            "id": "75e00e93",
                                            "settings": {
                                                "title": "No. of Vacancy :",
                                                "header_size": "h6",
                                                "align": "center",
                                                "align_mobile": "center",
                                                "_margin": {
                                                    "unit": "px",
                                                    "top": "0",
                                                    "right": "0",
                                                    "bottom": "8",
                                                    "left": "0",
                                                    "isLinked": false
                                                },
                                                "__globals__": {
                                                    "title_color": "globals\/colors?id=21bfb04",
                                                    "typography_typography": "globals\/typography?id=secondary"
                                                },
                                                "pa_condition_repeater": []
                                            },
                                            "elements": [],
                                            "isInner": false,
                                            "widgetType": "heading",
                                            "elType": "widget"
                                        },
                                        {
                                            "id": "13ac6177",
                                            "settings": {
                                                "title": "8",
                                                "header_size": "h5",
                                                "align": "center",
                                                "align_mobile": "center",
                                                "__globals__": {
                                                    "title_color": "globals\/colors?id=21bfb04",
                                                    "typography_typography": "globals\/typography?id=99dd0b2"
                                                },
                                                "pa_condition_repeater": []
                                            },
                                            "elements": [],
                                            "isInner": false,
                                            "widgetType": "heading",
                                            "elType": "widget"
                                        }
                                    ],
                                    "isInner": true,
                                    "elType": "column"
                                }
                            ],
                            "isInner": true,
                            "elType": "section"
                        },
                        {
                            "id": "7c65bfe2",
                            "settings": {
                                "image": {
                                    "id": 359,
                                    "url": "https:\/\/demo.bosathemes.com\/unbound\/wp-content\/uploads\/sites\/10\/2021\/08\/unbound-img02.jpg",
                                    "alt": "",
                                    "source": "library"
                                },
                                "image_size": "medium_large",
                                "_margin": {
                                    "unit": "px",
                                    "top": "0",
                                    "right": "0",
                                    "bottom": "30",
                                    "left": "0",
                                    "isLinked": false
                                },
                                "width": {
                                    "unit": "%",
                                    "size": 100,
                                    "sizes": []
                                },
                                "image_border_radius": {
                                    "unit": "px",
                                    "top": "0",
                                    "right": "0",
                                    "bottom": "25",
                                    "left": "25",
                                    "isLinked": false
                                },
                                "pa_condition_repeater": []
                            },
                            "elements": [],
                            "isInner": false,
                            "widgetType": "image",
                            "elType": "widget"
                        },
                        {
                            "id": "651dba32",
                            "settings": {
                                "tabs": [
                                    {
                                        "tab_title": "Description",
                                        "tab_content": "<p>Reprehenderit hic bibendum repellendus, repellat auctor! Integer temporibus, facilisis iaculis alias senectus, non quam molestiae incidunt cubilia, fuga? Quasi natoque dicta a fuga dapibus dolore molestie sociis erat, convallis quibusdam possimus semper nonummy mattis, quasi.<\/p><p>Autem nec quaerat cubilia magnam eu mauris hic hac nisi eos nobis officiis corrupti consequuntur molestie urna volutpat! Quos diamlorem convallis vestibulum doloremque iste facilisi.<\/p><ul><li>Nunc minima aspernatur dignissimos, sit adipiscing? Cupidatat cursus.<\/li><li>Netus donec justo mauris etiam velit.<\/li><li>Quis dolorum habitasse accusantium hic consequat.<\/li><li>Mus quasi aute non, at, saepe? Commodi sodales aliquam voluptatum.<\/li><li>Adipisicing ullamcorper dapibus, consequatur itaque eros orci odio.<\/li><li>Lobortis facere accusamus nemo, ipsum ad morbi.<\/li><li>Netus donec justo mauris etiam velit.<\/li><li>Quis dolorum habitasse accusantium hic consequat.<\/li><\/ul>",
                                        "_id": "57e6771"
                                    },
                                    {
                                        "tab_title": "Overview",
                                        "tab_content": "<h6><strong>#OVERVIEW<\/strong><\/h6><p>Reprehenderit hic bibendum repellendus, repellat auctor! Integer temporibus, facilisis iaculis alias senectus, non quam molestiae incidunt cubilia, fuga? Quasi natoque dicta a fuga dapibus dolore molestie sociis erat, convallis quibusdam possimus semper nonummy mattis, quasi.<\/p><p>Curae ad viverra odit porta, dolore, nascetur placeat. Exercitation vulputate modi rhoncus occaecat etiam erat cras erat cumque harum, repellendus. Voluptatem rem porttitor minim nihil.Curae ad viverra odit porta, dolore, nascetur placeat. Exercitation vulputate modi rhoncus occaecat etiam erat cras erat cumque harum, repellendus. Voluptatem rem porttitor minim nihil.<\/p>",
                                        "_id": "9828de9"
                                    },
                                    {
                                        "tab_title": "Requirement",
                                        "tab_content": "<p>Lorem ipsum dolor sit amet, consectetur adipiscing elit. Ut elit tellus, luctus nec ullamcorper mattis, pulvinar dapibus leo.Venenatis cupidatat rem sociosqu platea. Earum felis consequatur adipisci minus viverra, nullam molestias nibh conubia.<\/p><ul><li>Nunc minima aspernatur dignissimos, sit adipiscing? Cupidatat cursus.<\/li><li>Netus donec justo mauris etiam velit.<\/li><li>Quis dolorum habitasse accusantium hic consequat.<\/li><li>Mus quasi aute non, at, saepe? Commodi sodales aliquam voluptatum.<\/li><li>Adipisicing ullamcorper dapibus, consequatur itaque eros orci odio.<\/li><\/ul>",
                                        "_id": "7ed8416"
                                    }
                                ],
                                "border_color": "#F15B431C",
                                "content_typography_font_family": "Poppins",
                                "content_typography_font_size": {
                                    "unit": "px",
                                    "size": 16,
                                    "sizes": []
                                },
                                "content_typography_font_weight": "normal",
                                "content_typography_line_height": {
                                    "unit": "em",
                                    "size": 1.5,
                                    "sizes": []
                                },
                                "background_color": "#FFFFFF",
                                "__globals__": {
                                    "tab_active_color": "",
                                    "tab_typography_typography": "globals\/typography?id=secondary",
                                    "content_typography_typography": "",
                                    "border_color": "",
                                    "background_color": "globals\/colors?id=21bfb04",
                                    "tab_color": "globals\/colors?id=secondary"
                                },
                                "content_typography_text_transform": "none",
                                "tab_color": "#151515",
                                "pa_condition_repeater": []
                            },
                            "elements": [],
                            "isInner": false,
                            "widgetType": "tabs",
                            "elType": "widget"
                        }
                    ],
                    "isInner": false,
                    "elType": "column"
                }
            ],
            "isInner": false,
            "elType": "section"
        },
        {
            "id": "7893dd3f",
            "settings": {
                "gap": "no",
                "structure": "20",
                "background_background": "classic",
                "background_image": {
                    "url": "https:\/\/demo.bosathemes.com\/unbound\/wp-content\/uploads\/sites\/10\/2021\/08\/unbound-img06.jpg",
                    "id": 363,
                    "alt": "",
                    "source": "library"
                },
                "background_position": "center center",
                "background_repeat": "no-repeat",
                "background_size": "cover",
                "background_overlay_background": "classic",
                "background_overlay_opacity": {
                    "unit": "px",
                    "size": 0.7,
                    "sizes": []
                },
                "padding": {
                    "unit": "px",
                    "top": "100",
                    "right": "15",
                    "bottom": "100",
                    "left": "15",
                    "isLinked": false
                },
                "__globals__": {
                    "background_overlay_color": "globals\/colors?id=e5e9561"
                },
                "_title": "callback",
                "background_attachment": "fixed",
                "padding_mobile": {
                    "unit": "px",
                    "top": "80",
                    "right": "15",
                    "bottom": "80",
                    "left": "15",
                    "isLinked": false
                },
                "pa_condition_repeater": []
            },
            "elements": [
                {
                    "id": "3a835b5e",
                    "settings": {
                        "_column_size": 50,
                        "_inline_size": 57,
                        "_inline_size_tablet": 90,
                        "_inline_size_mobile": 100,
                        "background_background": "classic",
                        "background_overlay_background": "classic",
                        "background_overlay_opacity": {
                            "unit": "px",
                            "size": 0.7,
                            "sizes": []
                        },
                        "padding": {
                            "unit": "px",
                            "top": "50",
                            "right": "50",
                            "bottom": "50",
                            "left": "50",
                            "isLinked": true
                        },
                        "padding_mobile": {
                            "unit": "px",
                            "top": "35",
                            "right": "35",
                            "bottom": "35",
                            "left": "35",
                            "isLinked": true
                        },
                        "__globals__": {
                            "background_color": "",
                            "background_overlay_color": "globals\/colors?id=secondary"
                        },
                        "border_radius": {
                            "unit": "px",
                            "top": "25",
                            "right": "25",
                            "bottom": "25",
                            "left": "25",
                            "isLinked": true
                        },
                        "pa_condition_repeater": []
                    },
                    "elements": [
                        {
                            "id": "7ae8d08",
                            "settings": {
                                "title": "INVOLVE TODAY",
                                "header_size": "h5",
                                "__globals__": {
                                    "typography_typography": "globals\/typography?id=secondary",
                                    "title_color": "globals\/colors?id=21bfb04"
                                },
                                "align": "left",
                                "pa_condition_repeater": []
                            },
                            "elements": [],
                            "isInner": false,
                            "widgetType": "heading",
                            "elType": "widget"
                        },
                        {
                            "id": "2daa6284",
                            "settings": {
                                "title": "Trusted by more than 65,000 people !!",
                                "__globals__": {
                                    "title_color": "globals\/colors?id=21bfb04",
                                    "typography_typography": ""
                                },
                                "title_color": "#FFFFFF",
                                "typography_font_family": "Raleway",
                                "typography_font_size": {
                                    "unit": "px",
                                    "size": 48,
                                    "sizes": []
                                },
                                "typography_font_weight": "900",
                                "typography_line_height": {
                                    "unit": "em",
                                    "size": 1.1,
                                    "sizes": []
                                },
                                "header_size": "h3",
                                "pa_condition_repeater": []
                            },
                            "elements": [],
                            "isInner": false,
                            "widgetType": "heading",
                            "elType": "widget"
                        },
                        {
                            "id": "2d1d2f6e",
                            "settings": {
                                "editor": "<p>Lorem ipsum dolor sit amet, consectetur adipiscing elit. Ut elit tellus, luctus nec ullamcorper mattis, pulvinar dapibus leo. Eaque adipiscing, luctus eleifend temporibus occaecat luctus eleifend tempo ribus.<\/p>",
                                "__globals__": {
                                    "text_color": "globals\/colors?id=ad41708"
                                },
                                "pa_condition_repeater": []
                            },
                            "elements": [],
                            "isInner": false,
                            "widgetType": "text-editor",
                            "elType": "widget"
                        },
                        {
                            "id": "94a73f4",
                            "settings": {
                                "text": "JOIN US NOW",
                                "align": "left",
                                "typography_font_family": "Montserrat",
                                "typography_font_size": {
                                    "unit": "px",
                                    "size": 15,
                                    "sizes": []
                                },
                                "typography_font_weight": "600",
                                "typography_text_transform": "uppercase",
                                "typography_line_height": {
                                    "unit": "em",
                                    "size": 1,
                                    "sizes": []
                                },
                                "button_hover_border_color": "#030F27",
                                "border_width": {
                                    "unit": "px",
                                    "top": "1",
                                    "right": "1",
                                    "bottom": "1",
                                    "left": "1",
                                    "isLinked": true
                                },
                                "typography_font_size_mobile": {
                                    "unit": "px",
                                    "size": 15,
                                    "sizes": []
                                },
                                "align_mobile": "left",
                                "align_tablet": "left",
                                "pa_condition_repeater": []
                            },
                            "elements": [],
                            "isInner": false,
                            "widgetType": "button",
                            "elType": "widget"
                        }
                    ],
                    "isInner": false,
                    "elType": "column"
                },
                {
                    "id": "4a5c931d",
                    "settings": {
                        "_column_size": 50,
                        "_inline_size": 43,
                        "pa_condition_repeater": []
                    },
                    "elements": [],
                    "isInner": false,
                    "elType": "column"
                }
            ],
            "isInner": false,
            "elType": "section"
        }
    ],
    "page_settings": {
        "hide_title": "yes"
    }
}